{"@t":"2022-07-15T12:40:13.0408849Z","@mt":"Acquiring MainDom.","SourceContext":"Umbraco.Cms.Core.Runtime.MainDom","ProcessId":14344,"ProcessName":"KitBasico","ThreadId":1,"ApplicationId":"867c89341f884290be6f471178dcca1af0e1eed9","MachineName":"LAPTOP-RLDV270R","Log4NetLevel":"INFO "}
{"@t":"2022-07-15T12:40:13.0521320Z","@mt":"Acquired MainDom.","SourceContext":"Umbraco.Cms.Core.Runtime.MainDom","ProcessId":14344,"ProcessName":"KitBasico","ThreadId":1,"ApplicationId":"867c89341f884290be6f471178dcca1af0e1eed9","MachineName":"LAPTOP-RLDV270R","Log4NetLevel":"INFO "}
{"@t":"2022-07-15T12:40:14.3612570Z","@mt":"Now listening on: {address}","address":"https://localhost:44363","EventId":{"Id":14,"Name":"ListeningOnAddress"},"SourceContext":"Microsoft.Hosting.Lifetime","ProcessId":14344,"ProcessName":"KitBasico","ThreadId":1,"ApplicationId":"867c89341f884290be6f471178dcca1af0e1eed9","MachineName":"LAPTOP-RLDV270R","Log4NetLevel":"INFO "}
{"@t":"2022-07-15T12:40:14.3613450Z","@mt":"Now listening on: {address}","address":"http://localhost:29392","EventId":{"Id":14,"Name":"ListeningOnAddress"},"SourceContext":"Microsoft.Hosting.Lifetime","ProcessId":14344,"ProcessName":"KitBasico","ThreadId":1,"ApplicationId":"867c89341f884290be6f471178dcca1af0e1eed9","MachineName":"LAPTOP-RLDV270R","Log4NetLevel":"INFO "}
{"@t":"2022-07-15T12:40:14.3635310Z","@mt":"Application started. Press Ctrl+C to shut down.","SourceContext":"Microsoft.Hosting.Lifetime","ProcessId":14344,"ProcessName":"KitBasico","ThreadId":1,"ApplicationId":"867c89341f884290be6f471178dcca1af0e1eed9","MachineName":"LAPTOP-RLDV270R","Log4NetLevel":"INFO "}
{"@t":"2022-07-15T12:40:14.3635782Z","@mt":"Hosting environment: {envName}","envName":"Development","SourceContext":"Microsoft.Hosting.Lifetime","ProcessId":14344,"ProcessName":"KitBasico","ThreadId":1,"ApplicationId":"867c89341f884290be6f471178dcca1af0e1eed9","MachineName":"LAPTOP-RLDV270R","Log4NetLevel":"INFO "}
{"@t":"2022-07-15T12:40:14.3635950Z","@mt":"Content root path: {contentRoot}","contentRoot":"C:\\Users\\Mani\\Documents\\Work\\Learning\\Umbraco\\KitBasico","SourceContext":"Microsoft.Hosting.Lifetime","ProcessId":14344,"ProcessName":"KitBasico","ThreadId":1,"ApplicationId":"867c89341f884290be6f471178dcca1af0e1eed9","MachineName":"LAPTOP-RLDV270R","Log4NetLevel":"INFO "}
{"@t":"2022-07-15T12:40:28.6471925Z","@mt":"No umbracoApplicationUrl for service (yet), skip.","@l":"Warning","SourceContext":"Umbraco.Cms.Infrastructure.HostedServices.ServerRegistration.TouchServerTask","ProcessId":14344,"ProcessName":"KitBasico","ThreadId":7,"ApplicationId":"867c89341f884290be6f471178dcca1af0e1eed9","MachineName":"LAPTOP-RLDV270R","Log4NetLevel":"WARN "}
{"@t":"2022-07-15T12:41:28.6570769Z","@mt":"No umbracoApplicationUrl for service (yet), skip.","@l":"Warning","SourceContext":"Umbraco.Cms.Infrastructure.HostedServices.ServerRegistration.TouchServerTask","ProcessId":14344,"ProcessName":"KitBasico","ThreadId":14,"ApplicationId":"867c89341f884290be6f471178dcca1af0e1eed9","MachineName":"LAPTOP-RLDV270R","Log4NetLevel":"WARN "}
{"@t":"2022-07-15T12:42:28.6718697Z","@mt":"No umbracoApplicationUrl for service (yet), skip.","@l":"Warning","SourceContext":"Umbraco.Cms.Infrastructure.HostedServices.ServerRegistration.TouchServerTask","ProcessId":14344,"ProcessName":"KitBasico","ThreadId":12,"ApplicationId":"867c89341f884290be6f471178dcca1af0e1eed9","MachineName":"LAPTOP-RLDV270R","Log4NetLevel":"WARN "}
{"@t":"2022-07-15T12:43:28.6784663Z","@mt":"No umbracoApplicationUrl for service (yet), skip.","@l":"Warning","SourceContext":"Umbraco.Cms.Infrastructure.HostedServices.ServerRegistration.TouchServerTask","ProcessId":14344,"ProcessName":"KitBasico","ThreadId":4,"ApplicationId":"867c89341f884290be6f471178dcca1af0e1eed9","MachineName":"LAPTOP-RLDV270R","Log4NetLevel":"WARN "}
{"@t":"2022-07-15T12:44:28.6963434Z","@mt":"No umbracoApplicationUrl for service (yet), skip.","@l":"Warning","SourceContext":"Umbraco.Cms.Infrastructure.HostedServices.ServerRegistration.TouchServerTask","ProcessId":14344,"ProcessName":"KitBasico","ThreadId":14,"ApplicationId":"867c89341f884290be6f471178dcca1af0e1eed9","MachineName":"LAPTOP-RLDV270R","Log4NetLevel":"WARN "}
{"@t":"2022-07-15T12:45:28.7108539Z","@mt":"No umbracoApplicationUrl for service (yet), skip.","@l":"Warning","SourceContext":"Umbraco.Cms.Infrastructure.HostedServices.ServerRegistration.TouchServerTask","ProcessId":14344,"ProcessName":"KitBasico","ThreadId":26,"ApplicationId":"867c89341f884290be6f471178dcca1af0e1eed9","MachineName":"LAPTOP-RLDV270R","Log4NetLevel":"WARN "}
{"@t":"2022-07-15T12:46:28.7219685Z","@mt":"No umbracoApplicationUrl for service (yet), skip.","@l":"Warning","SourceContext":"Umbraco.Cms.Infrastructure.HostedServices.ServerRegistration.TouchServerTask","ProcessId":14344,"ProcessName":"KitBasico","ThreadId":24,"ApplicationId":"867c89341f884290be6f471178dcca1af0e1eed9","MachineName":"LAPTOP-RLDV270R","Log4NetLevel":"WARN "}
{"@t":"2022-07-15T12:47:28.7324272Z","@mt":"No umbracoApplicationUrl for service (yet), skip.","@l":"Warning","SourceContext":"Umbraco.Cms.Infrastructure.HostedServices.ServerRegistration.TouchServerTask","ProcessId":14344,"ProcessName":"KitBasico","ThreadId":35,"ApplicationId":"867c89341f884290be6f471178dcca1af0e1eed9","MachineName":"LAPTOP-RLDV270R","Log4NetLevel":"WARN "}
{"@t":"2022-07-15T12:48:28.7473044Z","@mt":"No umbracoApplicationUrl for service (yet), skip.","@l":"Warning","SourceContext":"Umbraco.Cms.Infrastructure.HostedServices.ServerRegistration.TouchServerTask","ProcessId":14344,"ProcessName":"KitBasico","ThreadId":39,"ApplicationId":"867c89341f884290be6f471178dcca1af0e1eed9","MachineName":"LAPTOP-RLDV270R","Log4NetLevel":"WARN "}
{"@t":"2022-07-15T12:49:28.7615081Z","@mt":"No umbracoApplicationUrl for service (yet), skip.","@l":"Warning","SourceContext":"Umbraco.Cms.Infrastructure.HostedServices.ServerRegistration.TouchServerTask","ProcessId":14344,"ProcessName":"KitBasico","ThreadId":48,"ApplicationId":"867c89341f884290be6f471178dcca1af0e1eed9","MachineName":"LAPTOP-RLDV270R","Log4NetLevel":"WARN "}
{"@t":"2022-07-15T12:50:28.7754353Z","@mt":"No umbracoApplicationUrl for service (yet), skip.","@l":"Warning","SourceContext":"Umbraco.Cms.Infrastructure.HostedServices.ServerRegistration.TouchServerTask","ProcessId":14344,"ProcessName":"KitBasico","ThreadId":40,"ApplicationId":"867c89341f884290be6f471178dcca1af0e1eed9","MachineName":"LAPTOP-RLDV270R","Log4NetLevel":"WARN "}
{"@t":"2022-07-15T12:51:28.7873001Z","@mt":"No umbracoApplicationUrl for service (yet), skip.","@l":"Warning","SourceContext":"Umbraco.Cms.Infrastructure.HostedServices.ServerRegistration.TouchServerTask","ProcessId":14344,"ProcessName":"KitBasico","ThreadId":45,"ApplicationId":"867c89341f884290be6f471178dcca1af0e1eed9","MachineName":"LAPTOP-RLDV270R","Log4NetLevel":"WARN "}
{"@t":"2022-07-15T12:52:28.7987592Z","@mt":"No umbracoApplicationUrl for service (yet), skip.","@l":"Warning","SourceContext":"Umbraco.Cms.Infrastructure.HostedServices.ServerRegistration.TouchServerTask","ProcessId":14344,"ProcessName":"KitBasico","ThreadId":54,"ApplicationId":"867c89341f884290be6f471178dcca1af0e1eed9","MachineName":"LAPTOP-RLDV270R","Log4NetLevel":"WARN "}
{"@t":"2022-07-15T12:53:28.8132301Z","@mt":"No umbracoApplicationUrl for service (yet), skip.","@l":"Warning","SourceContext":"Umbraco.Cms.Infrastructure.HostedServices.ServerRegistration.TouchServerTask","ProcessId":14344,"ProcessName":"KitBasico","ThreadId":49,"ApplicationId":"867c89341f884290be6f471178dcca1af0e1eed9","MachineName":"LAPTOP-RLDV270R","Log4NetLevel":"WARN "}
{"@t":"2022-07-15T12:54:28.8260354Z","@mt":"No umbracoApplicationUrl for service (yet), skip.","@l":"Warning","SourceContext":"Umbraco.Cms.Infrastructure.HostedServices.ServerRegistration.TouchServerTask","ProcessId":14344,"ProcessName":"KitBasico","ThreadId":63,"ApplicationId":"867c89341f884290be6f471178dcca1af0e1eed9","MachineName":"LAPTOP-RLDV270R","Log4NetLevel":"WARN "}
{"@t":"2022-07-15T12:55:28.8394507Z","@mt":"No umbracoApplicationUrl for service (yet), skip.","@l":"Warning","SourceContext":"Umbraco.Cms.Infrastructure.HostedServices.ServerRegistration.TouchServerTask","ProcessId":14344,"ProcessName":"KitBasico","ThreadId":52,"ApplicationId":"867c89341f884290be6f471178dcca1af0e1eed9","MachineName":"LAPTOP-RLDV270R","Log4NetLevel":"WARN "}
{"@t":"2022-07-15T12:56:28.8447687Z","@mt":"No umbracoApplicationUrl for service (yet), skip.","@l":"Warning","SourceContext":"Umbraco.Cms.Infrastructure.HostedServices.ServerRegistration.TouchServerTask","ProcessId":14344,"ProcessName":"KitBasico","ThreadId":67,"ApplicationId":"867c89341f884290be6f471178dcca1af0e1eed9","MachineName":"LAPTOP-RLDV270R","Log4NetLevel":"WARN "}
{"@t":"2022-07-15T12:57:28.8482513Z","@mt":"No umbracoApplicationUrl for service (yet), skip.","@l":"Warning","SourceContext":"Umbraco.Cms.Infrastructure.HostedServices.ServerRegistration.TouchServerTask","ProcessId":14344,"ProcessName":"KitBasico","ThreadId":47,"ApplicationId":"867c89341f884290be6f471178dcca1af0e1eed9","MachineName":"LAPTOP-RLDV270R","Log4NetLevel":"WARN "}
{"@t":"2022-07-15T12:58:28.8597221Z","@mt":"No umbracoApplicationUrl for service (yet), skip.","@l":"Warning","SourceContext":"Umbraco.Cms.Infrastructure.HostedServices.ServerRegistration.TouchServerTask","ProcessId":14344,"ProcessName":"KitBasico","ThreadId":77,"ApplicationId":"867c89341f884290be6f471178dcca1af0e1eed9","MachineName":"LAPTOP-RLDV270R","Log4NetLevel":"WARN "}
{"@t":"2022-07-15T12:59:28.8835262Z","@mt":"No umbracoApplicationUrl for service (yet), skip.","@l":"Warning","SourceContext":"Umbraco.Cms.Infrastructure.HostedServices.ServerRegistration.TouchServerTask","ProcessId":14344,"ProcessName":"KitBasico","ThreadId":77,"ApplicationId":"867c89341f884290be6f471178dcca1af0e1eed9","MachineName":"LAPTOP-RLDV270R","Log4NetLevel":"WARN "}
{"@t":"2022-07-15T13:00:28.9010004Z","@mt":"No umbracoApplicationUrl for service (yet), skip.","@l":"Warning","SourceContext":"Umbraco.Cms.Infrastructure.HostedServices.ServerRegistration.TouchServerTask","ProcessId":14344,"ProcessName":"KitBasico","ThreadId":84,"ApplicationId":"867c89341f884290be6f471178dcca1af0e1eed9","MachineName":"LAPTOP-RLDV270R","Log4NetLevel":"WARN "}
{"@t":"2022-07-15T13:01:28.9160079Z","@mt":"No umbracoApplicationUrl for service (yet), skip.","@l":"Warning","SourceContext":"Umbraco.Cms.Infrastructure.HostedServices.ServerRegistration.TouchServerTask","ProcessId":14344,"ProcessName":"KitBasico","ThreadId":80,"ApplicationId":"867c89341f884290be6f471178dcca1af0e1eed9","MachineName":"LAPTOP-RLDV270R","Log4NetLevel":"WARN "}
{"@t":"2022-07-15T13:02:28.9294904Z","@mt":"No umbracoApplicationUrl for service (yet), skip.","@l":"Warning","SourceContext":"Umbraco.Cms.Infrastructure.HostedServices.ServerRegistration.TouchServerTask","ProcessId":14344,"ProcessName":"KitBasico","ThreadId":93,"ApplicationId":"867c89341f884290be6f471178dcca1af0e1eed9","MachineName":"LAPTOP-RLDV270R","Log4NetLevel":"WARN "}
{"@t":"2022-07-15T13:03:28.9414344Z","@mt":"No umbracoApplicationUrl for service (yet), skip.","@l":"Warning","SourceContext":"Umbraco.Cms.Infrastructure.HostedServices.ServerRegistration.TouchServerTask","ProcessId":14344,"ProcessName":"KitBasico","ThreadId":80,"ApplicationId":"867c89341f884290be6f471178dcca1af0e1eed9","MachineName":"LAPTOP-RLDV270R","Log4NetLevel":"WARN "}
{"@t":"2022-07-15T13:04:28.9547329Z","@mt":"No umbracoApplicationUrl for service (yet), skip.","@l":"Warning","SourceContext":"Umbraco.Cms.Infrastructure.HostedServices.ServerRegistration.TouchServerTask","ProcessId":14344,"ProcessName":"KitBasico","ThreadId":101,"ApplicationId":"867c89341f884290be6f471178dcca1af0e1eed9","MachineName":"LAPTOP-RLDV270R","Log4NetLevel":"WARN "}
{"@t":"2022-07-15T13:05:28.9669591Z","@mt":"No umbracoApplicationUrl for service (yet), skip.","@l":"Warning","SourceContext":"Umbraco.Cms.Infrastructure.HostedServices.ServerRegistration.TouchServerTask","ProcessId":14344,"ProcessName":"KitBasico","ThreadId":92,"ApplicationId":"867c89341f884290be6f471178dcca1af0e1eed9","MachineName":"LAPTOP-RLDV270R","Log4NetLevel":"WARN "}
{"@t":"2022-07-15T13:06:28.9810367Z","@mt":"No umbracoApplicationUrl for service (yet), skip.","@l":"Warning","SourceContext":"Umbraco.Cms.Infrastructure.HostedServices.ServerRegistration.TouchServerTask","ProcessId":14344,"ProcessName":"KitBasico","ThreadId":92,"ApplicationId":"867c89341f884290be6f471178dcca1af0e1eed9","MachineName":"LAPTOP-RLDV270R","Log4NetLevel":"WARN "}
{"@t":"2022-07-15T13:07:28.9936839Z","@mt":"No umbracoApplicationUrl for service (yet), skip.","@l":"Warning","SourceContext":"Umbraco.Cms.Infrastructure.HostedServices.ServerRegistration.TouchServerTask","ProcessId":14344,"ProcessName":"KitBasico","ThreadId":115,"ApplicationId":"867c89341f884290be6f471178dcca1af0e1eed9","MachineName":"LAPTOP-RLDV270R","Log4NetLevel":"WARN "}
{"@t":"2022-07-15T13:08:29.0079889Z","@mt":"No umbracoApplicationUrl for service (yet), skip.","@l":"Warning","SourceContext":"Umbraco.Cms.Infrastructure.HostedServices.ServerRegistration.TouchServerTask","ProcessId":14344,"ProcessName":"KitBasico","ThreadId":118,"ApplicationId":"867c89341f884290be6f471178dcca1af0e1eed9","MachineName":"LAPTOP-RLDV270R","Log4NetLevel":"WARN "}
{"@t":"2022-07-15T13:09:29.0201182Z","@mt":"No umbracoApplicationUrl for service (yet), skip.","@l":"Warning","SourceContext":"Umbraco.Cms.Infrastructure.HostedServices.ServerRegistration.TouchServerTask","ProcessId":14344,"ProcessName":"KitBasico","ThreadId":130,"ApplicationId":"867c89341f884290be6f471178dcca1af0e1eed9","MachineName":"LAPTOP-RLDV270R","Log4NetLevel":"WARN "}
{"@t":"2022-07-15T13:10:29.0320435Z","@mt":"No umbracoApplicationUrl for service (yet), skip.","@l":"Warning","SourceContext":"Umbraco.Cms.Infrastructure.HostedServices.ServerRegistration.TouchServerTask","ProcessId":14344,"ProcessName":"KitBasico","ThreadId":130,"ApplicationId":"867c89341f884290be6f471178dcca1af0e1eed9","MachineName":"LAPTOP-RLDV270R","Log4NetLevel":"WARN "}
{"@t":"2022-07-15T13:11:29.0472921Z","@mt":"No umbracoApplicationUrl for service (yet), skip.","@l":"Warning","SourceContext":"Umbraco.Cms.Infrastructure.HostedServices.ServerRegistration.TouchServerTask","ProcessId":14344,"ProcessName":"KitBasico","ThreadId":119,"ApplicationId":"867c89341f884290be6f471178dcca1af0e1eed9","MachineName":"LAPTOP-RLDV270R","Log4NetLevel":"WARN "}
{"@t":"2022-07-15T13:12:29.0577203Z","@mt":"No umbracoApplicationUrl for service (yet), skip.","@l":"Warning","SourceContext":"Umbraco.Cms.Infrastructure.HostedServices.ServerRegistration.TouchServerTask","ProcessId":14344,"ProcessName":"KitBasico","ThreadId":114,"ApplicationId":"867c89341f884290be6f471178dcca1af0e1eed9","MachineName":"LAPTOP-RLDV270R","Log4NetLevel":"WARN "}
{"@t":"2022-07-15T13:13:29.0667055Z","@mt":"No umbracoApplicationUrl for service (yet), skip.","@l":"Warning","SourceContext":"Umbraco.Cms.Infrastructure.HostedServices.ServerRegistration.TouchServerTask","ProcessId":14344,"ProcessName":"KitBasico","ThreadId":131,"ApplicationId":"867c89341f884290be6f471178dcca1af0e1eed9","MachineName":"LAPTOP-RLDV270R","Log4NetLevel":"WARN "}
{"@t":"2022-07-15T13:14:29.0846153Z","@mt":"No umbracoApplicationUrl for service (yet), skip.","@l":"Warning","SourceContext":"Umbraco.Cms.Infrastructure.HostedServices.ServerRegistration.TouchServerTask","ProcessId":14344,"ProcessName":"KitBasico","ThreadId":106,"ApplicationId":"867c89341f884290be6f471178dcca1af0e1eed9","MachineName":"LAPTOP-RLDV270R","Log4NetLevel":"WARN "}
{"@t":"2022-07-15T13:15:29.0983472Z","@mt":"No umbracoApplicationUrl for service (yet), skip.","@l":"Warning","SourceContext":"Umbraco.Cms.Infrastructure.HostedServices.ServerRegistration.TouchServerTask","ProcessId":14344,"ProcessName":"KitBasico","ThreadId":110,"ApplicationId":"867c89341f884290be6f471178dcca1af0e1eed9","MachineName":"LAPTOP-RLDV270R","Log4NetLevel":"WARN "}
{"@t":"2022-07-15T13:16:29.1095952Z","@mt":"No umbracoApplicationUrl for service (yet), skip.","@l":"Warning","SourceContext":"Umbraco.Cms.Infrastructure.HostedServices.ServerRegistration.TouchServerTask","ProcessId":14344,"ProcessName":"KitBasico","ThreadId":101,"ApplicationId":"867c89341f884290be6f471178dcca1af0e1eed9","MachineName":"LAPTOP-RLDV270R","Log4NetLevel":"WARN "}
{"@t":"2022-07-15T13:17:29.1226012Z","@mt":"No umbracoApplicationUrl for service (yet), skip.","@l":"Warning","SourceContext":"Umbraco.Cms.Infrastructure.HostedServices.ServerRegistration.TouchServerTask","ProcessId":14344,"ProcessName":"KitBasico","ThreadId":110,"ApplicationId":"867c89341f884290be6f471178dcca1af0e1eed9","MachineName":"LAPTOP-RLDV270R","Log4NetLevel":"WARN "}
{"@t":"2022-07-15T13:18:29.1349058Z","@mt":"No umbracoApplicationUrl for service (yet), skip.","@l":"Warning","SourceContext":"Umbraco.Cms.Infrastructure.HostedServices.ServerRegistration.TouchServerTask","ProcessId":14344,"ProcessName":"KitBasico","ThreadId":104,"ApplicationId":"867c89341f884290be6f471178dcca1af0e1eed9","MachineName":"LAPTOP-RLDV270R","Log4NetLevel":"WARN "}
{"@t":"2022-07-15T13:19:26.1831511Z","@mt":"Stopping ({SignalSource})","SignalSource":"environment","SourceContext":"Umbraco.Cms.Core.Runtime.MainDom","ProcessId":14344,"ProcessName":"KitBasico","ThreadId":91,"ApplicationId":"867c89341f884290be6f471178dcca1af0e1eed9","MachineName":"LAPTOP-RLDV270R","Log4NetLevel":"INFO "}
{"@t":"2022-07-15T13:19:26.1879136Z","@mt":"Released ({SignalSource})","SignalSource":"environment","SourceContext":"Umbraco.Cms.Core.Runtime.MainDom","ProcessId":14344,"ProcessName":"KitBasico","ThreadId":91,"ApplicationId":"867c89341f884290be6f471178dcca1af0e1eed9","MachineName":"LAPTOP-RLDV270R","Log4NetLevel":"INFO "}
{"@t":"2022-07-15T13:19:26.1883706Z","@mt":"Application is shutting down...","SourceContext":"Microsoft.Hosting.Lifetime","ProcessId":14344,"ProcessName":"KitBasico","ThreadId":91,"ApplicationId":"867c89341f884290be6f471178dcca1af0e1eed9","MachineName":"LAPTOP-RLDV270R","Log4NetLevel":"INFO "}
{"@t":"2022-07-15T13:19:26.1931950Z","@mt":"Queued Hosted Service is stopping.","SourceContext":"Umbraco.Cms.Infrastructure.HostedServices.QueuedHostedService","ProcessId":14344,"ProcessName":"KitBasico","ThreadId":93,"ApplicationId":"867c89341f884290be6f471178dcca1af0e1eed9","MachineName":"LAPTOP-RLDV270R","Log4NetLevel":"INFO "}
{"@t":"2022-07-15T13:19:36.3935285Z","@mt":"Acquiring MainDom.","SourceContext":"Umbraco.Cms.Core.Runtime.MainDom","ProcessId":9976,"ProcessName":"KitBasico","ThreadId":1,"ApplicationId":"867c89341f884290be6f471178dcca1af0e1eed9","MachineName":"LAPTOP-RLDV270R","Log4NetLevel":"INFO "}
{"@t":"2022-07-15T13:19:36.4039206Z","@mt":"Acquired MainDom.","SourceContext":"Umbraco.Cms.Core.Runtime.MainDom","ProcessId":9976,"ProcessName":"KitBasico","ThreadId":1,"ApplicationId":"867c89341f884290be6f471178dcca1af0e1eed9","MachineName":"LAPTOP-RLDV270R","Log4NetLevel":"INFO "}
{"@t":"2022-07-15T13:19:37.0134709Z","@mt":"Now listening on: {address}","address":"https://localhost:44363","EventId":{"Id":14,"Name":"ListeningOnAddress"},"SourceContext":"Microsoft.Hosting.Lifetime","ProcessId":9976,"ProcessName":"KitBasico","ThreadId":1,"ApplicationId":"867c89341f884290be6f471178dcca1af0e1eed9","MachineName":"LAPTOP-RLDV270R","Log4NetLevel":"INFO "}
{"@t":"2022-07-15T13:19:37.0135588Z","@mt":"Now listening on: {address}","address":"http://localhost:29392","EventId":{"Id":14,"Name":"ListeningOnAddress"},"SourceContext":"Microsoft.Hosting.Lifetime","ProcessId":9976,"ProcessName":"KitBasico","ThreadId":1,"ApplicationId":"867c89341f884290be6f471178dcca1af0e1eed9","MachineName":"LAPTOP-RLDV270R","Log4NetLevel":"INFO "}
{"@t":"2022-07-15T13:19:37.0158347Z","@mt":"Application started. Press Ctrl+C to shut down.","SourceContext":"Microsoft.Hosting.Lifetime","ProcessId":9976,"ProcessName":"KitBasico","ThreadId":1,"ApplicationId":"867c89341f884290be6f471178dcca1af0e1eed9","MachineName":"LAPTOP-RLDV270R","Log4NetLevel":"INFO "}
{"@t":"2022-07-15T13:19:37.0158775Z","@mt":"Hosting environment: {envName}","envName":"Development","SourceContext":"Microsoft.Hosting.Lifetime","ProcessId":9976,"ProcessName":"KitBasico","ThreadId":1,"ApplicationId":"867c89341f884290be6f471178dcca1af0e1eed9","MachineName":"LAPTOP-RLDV270R","Log4NetLevel":"INFO "}
{"@t":"2022-07-15T13:19:37.0159016Z","@mt":"Content root path: {contentRoot}","contentRoot":"C:\\Users\\Mani\\Documents\\Work\\Learning\\Umbraco\\KitBasico","SourceContext":"Microsoft.Hosting.Lifetime","ProcessId":9976,"ProcessName":"KitBasico","ThreadId":1,"ApplicationId":"867c89341f884290be6f471178dcca1af0e1eed9","MachineName":"LAPTOP-RLDV270R","Log4NetLevel":"INFO "}
{"@t":"2022-07-15T13:19:51.7112461Z","@mt":"No umbracoApplicationUrl for service (yet), skip.","@l":"Warning","SourceContext":"Umbraco.Cms.Infrastructure.HostedServices.ServerRegistration.TouchServerTask","ProcessId":9976,"ProcessName":"KitBasico","ThreadId":18,"ApplicationId":"867c89341f884290be6f471178dcca1af0e1eed9","MachineName":"LAPTOP-RLDV270R","Log4NetLevel":"WARN "}
{"@t":"2022-07-15T13:20:51.7306121Z","@mt":"No umbracoApplicationUrl for service (yet), skip.","@l":"Warning","SourceContext":"Umbraco.Cms.Infrastructure.HostedServices.ServerRegistration.TouchServerTask","ProcessId":9976,"ProcessName":"KitBasico","ThreadId":23,"ApplicationId":"867c89341f884290be6f471178dcca1af0e1eed9","MachineName":"LAPTOP-RLDV270R","Log4NetLevel":"WARN "}
{"@t":"2022-07-15T13:21:05.4639465Z","@mt":"Registered with MainDom, localContentDbExists? {LocalContentDbExists}, localMediaDbExists? {LocalMediaDbExists}","LocalContentDbExists":false,"LocalMediaDbExists":false,"SourceContext":"Umbraco.Cms.Infrastructure.PublishedCache.PublishedSnapshotService","RequestId":"0HMJ6CJFFJUSU:00000001","RequestPath":"/","ConnectionId":"0HMJ6CJFFJUSU","ProcessId":9976,"ProcessName":"KitBasico","ThreadId":7,"ApplicationId":"867c89341f884290be6f471178dcca1af0e1eed9","MachineName":"LAPTOP-RLDV270R","Log4NetLevel":"INFO ","HttpRequestId":"83fd09d9-5f35-457d-9f9f-10eee1889cc1","HttpRequestNumber":1,"HttpSessionId":"0"}
{"@t":"2022-07-15T13:21:05.4665313Z","@mt":"Creating the content store, localContentDbExists? {LocalContentDbExists}","LocalContentDbExists":false,"SourceContext":"Umbraco.Cms.Infrastructure.PublishedCache.PublishedSnapshotService","RequestId":"0HMJ6CJFFJUSU:00000001","RequestPath":"/","ConnectionId":"0HMJ6CJFFJUSU","ProcessId":9976,"ProcessName":"KitBasico","ThreadId":7,"ApplicationId":"867c89341f884290be6f471178dcca1af0e1eed9","MachineName":"LAPTOP-RLDV270R","Log4NetLevel":"INFO ","HttpRequestId":"83fd09d9-5f35-457d-9f9f-10eee1889cc1","HttpRequestNumber":1,"HttpSessionId":"0"}
{"@t":"2022-07-15T13:21:05.4682996Z","@mt":"Creating the media store, localMediaDbExists? {LocalMediaDbExists}","LocalMediaDbExists":false,"SourceContext":"Umbraco.Cms.Infrastructure.PublishedCache.PublishedSnapshotService","RequestId":"0HMJ6CJFFJUSU:00000001","RequestPath":"/","ConnectionId":"0HMJ6CJFFJUSU","ProcessId":9976,"ProcessName":"KitBasico","ThreadId":7,"ApplicationId":"867c89341f884290be6f471178dcca1af0e1eed9","MachineName":"LAPTOP-RLDV270R","Log4NetLevel":"INFO ","HttpRequestId":"83fd09d9-5f35-457d-9f9f-10eee1889cc1","HttpRequestNumber":1,"HttpSessionId":"0"}
{"@t":"2022-07-15T13:21:05.6305328Z","@mt":"{StartMessage} [Timing {TimingId}]","StartMessage":"Loading content from database","TimingId":"12aa2f8","SourceContext":"Umbraco.Cms.Core.Logging.ProfilingLogger","RequestId":"0HMJ6CJFFJUSU:00000001","RequestPath":"/","ConnectionId":"0HMJ6CJFFJUSU","ProcessId":9976,"ProcessName":"KitBasico","ThreadId":7,"ApplicationId":"867c89341f884290be6f471178dcca1af0e1eed9","MachineName":"LAPTOP-RLDV270R","Log4NetLevel":"INFO ","HttpRequestId":"83fd09d9-5f35-457d-9f9f-10eee1889cc1","HttpRequestNumber":1,"HttpSessionId":"0"}
{"@t":"2022-07-15T13:21:05.7173316Z","@mt":"{EndMessage} ({Duration}ms) [Timing {TimingId}]","EndMessage":"Completed.","Duration":86,"TimingId":"12aa2f8","SourceContext":"Umbraco.Cms.Core.Logging.ProfilingLogger","RequestId":"0HMJ6CJFFJUSU:00000001","RequestPath":"/","ConnectionId":"0HMJ6CJFFJUSU","ProcessId":9976,"ProcessName":"KitBasico","ThreadId":7,"ApplicationId":"867c89341f884290be6f471178dcca1af0e1eed9","MachineName":"LAPTOP-RLDV270R","Log4NetLevel":"INFO ","HttpRequestId":"83fd09d9-5f35-457d-9f9f-10eee1889cc1","HttpRequestNumber":1,"HttpSessionId":"0"}
{"@t":"2022-07-15T13:21:05.9096653Z","@mt":"{StartMessage} [Timing {TimingId}]","StartMessage":"Loading media from database","TimingId":"95a00f4","SourceContext":"Umbraco.Cms.Core.Logging.ProfilingLogger","RequestId":"0HMJ6CJFFJUSU:00000001","RequestPath":"/","ConnectionId":"0HMJ6CJFFJUSU","ProcessId":9976,"ProcessName":"KitBasico","ThreadId":7,"ApplicationId":"867c89341f884290be6f471178dcca1af0e1eed9","MachineName":"LAPTOP-RLDV270R","Log4NetLevel":"INFO ","HttpRequestId":"83fd09d9-5f35-457d-9f9f-10eee1889cc1","HttpRequestNumber":1,"HttpSessionId":"0"}
{"@t":"2022-07-15T13:21:05.9229561Z","@mt":"{EndMessage} ({Duration}ms) [Timing {TimingId}]","EndMessage":"Completed.","Duration":13,"TimingId":"95a00f4","SourceContext":"Umbraco.Cms.Core.Logging.ProfilingLogger","RequestId":"0HMJ6CJFFJUSU:00000001","RequestPath":"/","ConnectionId":"0HMJ6CJFFJUSU","ProcessId":9976,"ProcessName":"KitBasico","ThreadId":7,"ApplicationId":"867c89341f884290be6f471178dcca1af0e1eed9","MachineName":"LAPTOP-RLDV270R","Log4NetLevel":"INFO ","HttpRequestId":"83fd09d9-5f35-457d-9f9f-10eee1889cc1","HttpRequestNumber":1,"HttpSessionId":"0"}
{"@t":"2022-07-15T13:41:05.8674865Z","@mt":"User logged will be logged out due to timeout: {Username}, IP Address: {IPAddress}","Username":"mani@mkportal.co.uk","IPAddress":"::1","SourceContext":"Umbraco.Cms.Web.BackOffice.Controllers.AuthenticationController","ActionId":"0c29693f-109b-417c-80f0-bdd7e345aa27","ActionName":"Umbraco.Cms.Web.BackOffice.Controllers.AuthenticationController.GetRemainingTimeoutSeconds (Umbraco.Web.BackOffice)","RequestId":"0HMJ6CJFFJUSU:000000EB","RequestPath":"/umbraco/backoffice/umbracoapi/authentication/GetRemainingTimeoutSeconds","ConnectionId":"0HMJ6CJFFJUSU","ProcessId":9976,"ProcessName":"KitBasico","ThreadId":283,"ApplicationId":"867c89341f884290be6f471178dcca1af0e1eed9","MachineName":"LAPTOP-RLDV270R","Log4NetLevel":"INFO ","HttpRequestId":"3c89b86f-4ef4-4933-b132-13f68a941023","HttpRequestNumber":2,"HttpSessionId":"d7f03feb-e759-2fd8-438a-13dd5077c24e"}
