{"@t":"2022-08-10T10:46:37.7279707Z","@mt":"Acquiring MainDom.","SourceContext":"Umbraco.Cms.Core.Runtime.MainDom","ProcessId":14120,"ProcessName":"KitBasico","ThreadId":1,"ApplicationId":"82e9319c75fee66141d13b00f453b3d46969c2da","MachineName":"LAPTOP-RLDV270R","Log4NetLevel":"INFO "}
{"@t":"2022-08-10T10:46:37.7387079Z","@mt":"Acquired MainDom.","SourceContext":"Umbraco.Cms.Core.Runtime.MainDom","ProcessId":14120,"ProcessName":"KitBasico","ThreadId":1,"ApplicationId":"82e9319c75fee66141d13b00f453b3d46969c2da","MachineName":"LAPTOP-RLDV270R","Log4NetLevel":"INFO "}
{"@t":"2022-08-10T10:46:38.7209541Z","@mt":"Now listening on: {address}","address":"https://localhost:44363","EventId":{"Id":14,"Name":"ListeningOnAddress"},"SourceContext":"Microsoft.Hosting.Lifetime","ProcessId":14120,"ProcessName":"KitBasico","ThreadId":1,"ApplicationId":"82e9319c75fee66141d13b00f453b3d46969c2da","MachineName":"LAPTOP-RLDV270R","Log4NetLevel":"INFO "}
{"@t":"2022-08-10T10:46:38.7211043Z","@mt":"Now listening on: {address}","address":"http://localhost:29392","EventId":{"Id":14,"Name":"ListeningOnAddress"},"SourceContext":"Microsoft.Hosting.Lifetime","ProcessId":14120,"ProcessName":"KitBasico","ThreadId":1,"ApplicationId":"82e9319c75fee66141d13b00f453b3d46969c2da","MachineName":"LAPTOP-RLDV270R","Log4NetLevel":"INFO "}
{"@t":"2022-08-10T10:46:38.7237072Z","@mt":"Application started. Press Ctrl+C to shut down.","SourceContext":"Microsoft.Hosting.Lifetime","ProcessId":14120,"ProcessName":"KitBasico","ThreadId":1,"ApplicationId":"82e9319c75fee66141d13b00f453b3d46969c2da","MachineName":"LAPTOP-RLDV270R","Log4NetLevel":"INFO "}
{"@t":"2022-08-10T10:46:38.7237531Z","@mt":"Hosting environment: {envName}","envName":"Development","SourceContext":"Microsoft.Hosting.Lifetime","ProcessId":14120,"ProcessName":"KitBasico","ThreadId":1,"ApplicationId":"82e9319c75fee66141d13b00f453b3d46969c2da","MachineName":"LAPTOP-RLDV270R","Log4NetLevel":"INFO "}
{"@t":"2022-08-10T10:46:38.7237641Z","@mt":"Content root path: {contentRoot}","contentRoot":"C:\\Users\\Mani\\Documents\\Work\\Learning\\Umbraco\\kitbasico","SourceContext":"Microsoft.Hosting.Lifetime","ProcessId":14120,"ProcessName":"KitBasico","ThreadId":1,"ApplicationId":"82e9319c75fee66141d13b00f453b3d46969c2da","MachineName":"LAPTOP-RLDV270R","Log4NetLevel":"INFO "}
{"@t":"2022-08-10T10:46:53.0357944Z","@mt":"No umbracoApplicationUrl for service (yet), skip.","@l":"Warning","SourceContext":"Umbraco.Cms.Infrastructure.HostedServices.ServerRegistration.TouchServerTask","ProcessId":14120,"ProcessName":"KitBasico","ThreadId":19,"ApplicationId":"82e9319c75fee66141d13b00f453b3d46969c2da","MachineName":"LAPTOP-RLDV270R","Log4NetLevel":"WARN "}
{"@t":"2022-08-10T10:47:53.0367535Z","@mt":"No umbracoApplicationUrl for service (yet), skip.","@l":"Warning","SourceContext":"Umbraco.Cms.Infrastructure.HostedServices.ServerRegistration.TouchServerTask","ProcessId":14120,"ProcessName":"KitBasico","ThreadId":20,"ApplicationId":"82e9319c75fee66141d13b00f453b3d46969c2da","MachineName":"LAPTOP-RLDV270R","Log4NetLevel":"WARN "}
{"@t":"2022-08-10T10:48:53.0547714Z","@mt":"No umbracoApplicationUrl for service (yet), skip.","@l":"Warning","SourceContext":"Umbraco.Cms.Infrastructure.HostedServices.ServerRegistration.TouchServerTask","ProcessId":14120,"ProcessName":"KitBasico","ThreadId":20,"ApplicationId":"82e9319c75fee66141d13b00f453b3d46969c2da","MachineName":"LAPTOP-RLDV270R","Log4NetLevel":"WARN "}
{"@t":"2022-08-10T10:49:53.0686340Z","@mt":"No umbracoApplicationUrl for service (yet), skip.","@l":"Warning","SourceContext":"Umbraco.Cms.Infrastructure.HostedServices.ServerRegistration.TouchServerTask","ProcessId":14120,"ProcessName":"KitBasico","ThreadId":24,"ApplicationId":"82e9319c75fee66141d13b00f453b3d46969c2da","MachineName":"LAPTOP-RLDV270R","Log4NetLevel":"WARN "}
{"@t":"2022-08-10T11:05:18.4320129Z","@mt":"Registered with MainDom, localContentDbExists? {LocalContentDbExists}, localMediaDbExists? {LocalMediaDbExists}","LocalContentDbExists":true,"LocalMediaDbExists":true,"SourceContext":"Umbraco.Cms.Infrastructure.PublishedCache.PublishedSnapshotService","RequestId":"0HMJQNO4L6S6A:000000C9","RequestPath":"/","ConnectionId":"0HMJQNO4L6S6A","ProcessId":14120,"ProcessName":"KitBasico","ThreadId":180,"ApplicationId":"82e9319c75fee66141d13b00f453b3d46969c2da","MachineName":"LAPTOP-RLDV270R","Log4NetLevel":"INFO ","HttpRequestId":"57f2ed18-192e-46c6-8ed1-a333cf9a423e","HttpRequestNumber":1,"HttpSessionId":"0"}
{"@t":"2022-08-10T11:05:18.4361279Z","@mt":"Creating the content store, localContentDbExists? {LocalContentDbExists}","LocalContentDbExists":true,"SourceContext":"Umbraco.Cms.Infrastructure.PublishedCache.PublishedSnapshotService","RequestId":"0HMJQNO4L6S6A:000000C9","RequestPath":"/","ConnectionId":"0HMJQNO4L6S6A","ProcessId":14120,"ProcessName":"KitBasico","ThreadId":180,"ApplicationId":"82e9319c75fee66141d13b00f453b3d46969c2da","MachineName":"LAPTOP-RLDV270R","Log4NetLevel":"INFO ","HttpRequestId":"57f2ed18-192e-46c6-8ed1-a333cf9a423e","HttpRequestNumber":1,"HttpSessionId":"0"}
{"@t":"2022-08-10T11:05:18.4395823Z","@mt":"Creating the media store, localMediaDbExists? {LocalMediaDbExists}","LocalMediaDbExists":true,"SourceContext":"Umbraco.Cms.Infrastructure.PublishedCache.PublishedSnapshotService","RequestId":"0HMJQNO4L6S6A:000000C9","RequestPath":"/","ConnectionId":"0HMJQNO4L6S6A","ProcessId":14120,"ProcessName":"KitBasico","ThreadId":180,"ApplicationId":"82e9319c75fee66141d13b00f453b3d46969c2da","MachineName":"LAPTOP-RLDV270R","Log4NetLevel":"INFO ","HttpRequestId":"57f2ed18-192e-46c6-8ed1-a333cf9a423e","HttpRequestNumber":1,"HttpSessionId":"0"}
{"@t":"2022-08-10T11:05:18.5184836Z","@mt":"{StartMessage} [Timing {TimingId}]","StartMessage":"Loading content from local cache file","TimingId":"8df4eda","SourceContext":"Umbraco.Cms.Core.Logging.ProfilingLogger","RequestId":"0HMJQNO4L6S6A:000000C9","RequestPath":"/","ConnectionId":"0HMJQNO4L6S6A","ProcessId":14120,"ProcessName":"KitBasico","ThreadId":180,"ApplicationId":"82e9319c75fee66141d13b00f453b3d46969c2da","MachineName":"LAPTOP-RLDV270R","Log4NetLevel":"INFO ","HttpRequestId":"57f2ed18-192e-46c6-8ed1-a333cf9a423e","HttpRequestNumber":1,"HttpSessionId":"0"}
{"@t":"2022-08-10T11:05:18.5433728Z","@mt":"{EndMessage} ({Duration}ms) [Timing {TimingId}]","EndMessage":"Completed.","Duration":25,"TimingId":"8df4eda","SourceContext":"Umbraco.Cms.Core.Logging.ProfilingLogger","RequestId":"0HMJQNO4L6S6A:000000C9","RequestPath":"/","ConnectionId":"0HMJQNO4L6S6A","ProcessId":14120,"ProcessName":"KitBasico","ThreadId":180,"ApplicationId":"82e9319c75fee66141d13b00f453b3d46969c2da","MachineName":"LAPTOP-RLDV270R","Log4NetLevel":"INFO ","HttpRequestId":"57f2ed18-192e-46c6-8ed1-a333cf9a423e","HttpRequestNumber":1,"HttpSessionId":"0"}
{"@t":"2022-08-10T11:05:18.5495058Z","@mt":"{StartMessage} [Timing {TimingId}]","StartMessage":"Loading media from local cache file","TimingId":"5fa7c2e","SourceContext":"Umbraco.Cms.Core.Logging.ProfilingLogger","RequestId":"0HMJQNO4L6S6A:000000C9","RequestPath":"/","ConnectionId":"0HMJQNO4L6S6A","ProcessId":14120,"ProcessName":"KitBasico","ThreadId":180,"ApplicationId":"82e9319c75fee66141d13b00f453b3d46969c2da","MachineName":"LAPTOP-RLDV270R","Log4NetLevel":"INFO ","HttpRequestId":"57f2ed18-192e-46c6-8ed1-a333cf9a423e","HttpRequestNumber":1,"HttpSessionId":"0"}
{"@t":"2022-08-10T11:05:18.5498975Z","@mt":"Tried to load {entityType} from the local cache file but it was empty.","entityType":"media","SourceContext":"Umbraco.Cms.Infrastructure.PublishedCache.PublishedSnapshotService","RequestId":"0HMJQNO4L6S6A:000000C9","RequestPath":"/","ConnectionId":"0HMJQNO4L6S6A","ProcessId":14120,"ProcessName":"KitBasico","ThreadId":180,"ApplicationId":"82e9319c75fee66141d13b00f453b3d46969c2da","MachineName":"LAPTOP-RLDV270R","Log4NetLevel":"INFO ","HttpRequestId":"57f2ed18-192e-46c6-8ed1-a333cf9a423e","HttpRequestNumber":1,"HttpSessionId":"0"}
{"@t":"2022-08-10T11:05:18.5499396Z","@mt":"{EndMessage} ({Duration}ms) [Timing {TimingId}]","EndMessage":"Completed.","Duration":0,"TimingId":"5fa7c2e","SourceContext":"Umbraco.Cms.Core.Logging.ProfilingLogger","RequestId":"0HMJQNO4L6S6A:000000C9","RequestPath":"/","ConnectionId":"0HMJQNO4L6S6A","ProcessId":14120,"ProcessName":"KitBasico","ThreadId":180,"ApplicationId":"82e9319c75fee66141d13b00f453b3d46969c2da","MachineName":"LAPTOP-RLDV270R","Log4NetLevel":"INFO ","HttpRequestId":"57f2ed18-192e-46c6-8ed1-a333cf9a423e","HttpRequestNumber":1,"HttpSessionId":"0"}
{"@t":"2022-08-10T11:05:18.5499842Z","@mt":"Loading media from local db raised warnings, will reload from database.","@l":"Warning","SourceContext":"Umbraco.Cms.Infrastructure.PublishedCache.PublishedSnapshotService","RequestId":"0HMJQNO4L6S6A:000000C9","RequestPath":"/","ConnectionId":"0HMJQNO4L6S6A","ProcessId":14120,"ProcessName":"KitBasico","ThreadId":180,"ApplicationId":"82e9319c75fee66141d13b00f453b3d46969c2da","MachineName":"LAPTOP-RLDV270R","Log4NetLevel":"WARN ","HttpRequestId":"57f2ed18-192e-46c6-8ed1-a333cf9a423e","HttpRequestNumber":1,"HttpSessionId":"0"}
{"@t":"2022-08-10T11:05:18.5522182Z","@mt":"{StartMessage} [Timing {TimingId}]","StartMessage":"Loading media from database","TimingId":"6937312","SourceContext":"Umbraco.Cms.Core.Logging.ProfilingLogger","RequestId":"0HMJQNO4L6S6A:000000C9","RequestPath":"/","ConnectionId":"0HMJQNO4L6S6A","ProcessId":14120,"ProcessName":"KitBasico","ThreadId":180,"ApplicationId":"82e9319c75fee66141d13b00f453b3d46969c2da","MachineName":"LAPTOP-RLDV270R","Log4NetLevel":"INFO ","HttpRequestId":"57f2ed18-192e-46c6-8ed1-a333cf9a423e","HttpRequestNumber":1,"HttpSessionId":"0"}
{"@t":"2022-08-10T11:05:18.6058175Z","@mt":"{EndMessage} ({Duration}ms) [Timing {TimingId}]","EndMessage":"Completed.","Duration":53,"TimingId":"6937312","SourceContext":"Umbraco.Cms.Core.Logging.ProfilingLogger","RequestId":"0HMJQNO4L6S6A:000000C9","RequestPath":"/","ConnectionId":"0HMJQNO4L6S6A","ProcessId":14120,"ProcessName":"KitBasico","ThreadId":180,"ApplicationId":"82e9319c75fee66141d13b00f453b3d46969c2da","MachineName":"LAPTOP-RLDV270R","Log4NetLevel":"INFO ","HttpRequestId":"57f2ed18-192e-46c6-8ed1-a333cf9a423e","HttpRequestNumber":1,"HttpSessionId":"0"}
{"@t":"2022-08-10T11:09:44.2288742Z","@mt":"User logged will be logged out due to timeout: {Username}, IP Address: {IPAddress}","Username":"mani@mkportal.co.uk","IPAddress":"::1","SourceContext":"Umbraco.Cms.Web.BackOffice.Controllers.AuthenticationController","ActionId":"3e1ba797-c066-49e7-937b-e89101f1ac21","ActionName":"Umbraco.Cms.Web.BackOffice.Controllers.AuthenticationController.GetRemainingTimeoutSeconds (Umbraco.Web.BackOffice)","RequestId":"0HMJQNO4L6S6A:00000131","RequestPath":"/umbraco/backoffice/umbracoapi/authentication/GetRemainingTimeoutSeconds","ConnectionId":"0HMJQNO4L6S6A","ProcessId":14120,"ProcessName":"KitBasico","ThreadId":178,"ApplicationId":"82e9319c75fee66141d13b00f453b3d46969c2da","MachineName":"LAPTOP-RLDV270R","Log4NetLevel":"INFO ","HttpRequestId":"d8bd5ca1-55b7-4f3f-a0b6-1491be1bc940","HttpRequestNumber":2,"HttpSessionId":"7436f660-182a-6f6a-1612-cf9e55435349"}
{"@t":"2022-08-10T11:22:32.6923671Z","@mt":"Document {ContentName} (id={ContentId}) has been published.","ContentName":"Home","ContentId":1126,"SourceContext":"Umbraco.Cms.Core.Services.ContentService","ActionId":"7985666b-1589-457d-a171-851c5e79292f","ActionName":"Umbraco.Cms.Web.BackOffice.Controllers.ContentController.PostSave (Umbraco.Web.BackOffice)","RequestId":"0HMJQNO4L6S6I:00000067","RequestPath":"/umbraco/backoffice/umbracoapi/content/PostSave","ConnectionId":"0HMJQNO4L6S6I","ProcessId":14120,"ProcessName":"KitBasico","ThreadId":278,"ApplicationId":"82e9319c75fee66141d13b00f453b3d46969c2da","MachineName":"LAPTOP-RLDV270R","Log4NetLevel":"INFO ","HttpRequestId":"572694de-3d73-48b2-8b34-3321daed4ff2","HttpRequestNumber":3,"HttpSessionId":"02415d39-e71a-04aa-9e91-e105198c2365"}
{"@t":"2022-08-10T11:22:33.1396020Z","@mt":"Adding examine event handlers for {RegisteredIndexers} index providers.","RegisteredIndexers":3,"SourceContext":"Umbraco.Cms.Infrastructure.Examine.ExamineUmbracoIndexingHandler","ActionId":"7985666b-1589-457d-a171-851c5e79292f","ActionName":"Umbraco.Cms.Web.BackOffice.Controllers.ContentController.PostSave (Umbraco.Web.BackOffice)","RequestId":"0HMJQNO4L6S6I:00000067","RequestPath":"/umbraco/backoffice/umbracoapi/content/PostSave","ConnectionId":"0HMJQNO4L6S6I","ProcessId":14120,"ProcessName":"KitBasico","ThreadId":278,"ApplicationId":"82e9319c75fee66141d13b00f453b3d46969c2da","MachineName":"LAPTOP-RLDV270R","Log4NetLevel":"INFO ","HttpRequestId":"572694de-3d73-48b2-8b34-3321daed4ff2","HttpRequestNumber":3,"HttpSessionId":"02415d39-e71a-04aa-9e91-e105198c2365"}
{"@t":"2022-08-10T11:42:13.2182375Z","@mt":"User logged will be logged out due to timeout: {Username}, IP Address: {IPAddress}","Username":"mani@mkportal.co.uk","IPAddress":"::1","SourceContext":"Umbraco.Cms.Web.BackOffice.Controllers.AuthenticationController","ActionId":"3e1ba797-c066-49e7-937b-e89101f1ac21","ActionName":"Umbraco.Cms.Web.BackOffice.Controllers.AuthenticationController.GetRemainingTimeoutSeconds (Umbraco.Web.BackOffice)","RequestId":"0HMJQNO4L6S6I:00000099","RequestPath":"/umbraco/backoffice/umbracoapi/authentication/GetRemainingTimeoutSeconds","ConnectionId":"0HMJQNO4L6S6I","ProcessId":14120,"ProcessName":"KitBasico","ThreadId":427,"ApplicationId":"82e9319c75fee66141d13b00f453b3d46969c2da","MachineName":"LAPTOP-RLDV270R","Log4NetLevel":"INFO ","HttpRequestId":"f8c93ca7-c582-4c5d-876e-4bb934f6d4ce","HttpRequestNumber":4,"HttpSessionId":"f689048f-3ac5-7748-27f9-78f5200d2811"}
{"@t":"2022-08-10T14:43:48.4533753Z","@mt":"Document {ContentName} (id={ContentId}) has been published.","ContentName":"Home","ContentId":1126,"SourceContext":"Umbraco.Cms.Core.Services.ContentService","ActionId":"7985666b-1589-457d-a171-851c5e79292f","ActionName":"Umbraco.Cms.Web.BackOffice.Controllers.ContentController.PostSave (Umbraco.Web.BackOffice)","RequestId":"0HMJQNO4L6S7S:00000011","RequestPath":"/umbraco/backoffice/umbracoapi/content/PostSave","ConnectionId":"0HMJQNO4L6S7S","ProcessId":14120,"ProcessName":"KitBasico","ThreadId":379,"ApplicationId":"82e9319c75fee66141d13b00f453b3d46969c2da","MachineName":"LAPTOP-RLDV270R","Log4NetLevel":"INFO ","HttpRequestId":"191f2180-fdbc-4d9d-b01a-fa7bf649b8a3","HttpRequestNumber":5,"HttpSessionId":"495aa787-b9fa-41d4-0c78-f7ca995aa369"}
